mailman3_fedmsg_plugin_schemas/__init__.py
mailman3_fedmsg_plugin_schemas/schemas.py
mailman3_fedmsg_plugin_schemas-1.0.0.dist-info/METADATA
mailman3_fedmsg_plugin_schemas-1.0.0.dist-info/WHEEL
mailman3_fedmsg_plugin_schemas-1.0.0.dist-info/entry_points.txt
mailman3_fedmsg_plugin_schemas-1.0.0.dist-info/RECORD
